datacat/__init__.py
datacat/auth.py
datacat/cli.py
datacat/client.py
datacat/config.py
datacat/error.py
datacat/http_client.py
datacat/model.py
datacat/srs.py
datacat-0.5.dist-info/DESCRIPTION.rst
datacat-0.5.dist-info/METADATA
datacat-0.5.dist-info/RECORD
datacat-0.5.dist-info/WHEEL
datacat-0.5.dist-info/entry_points.txt
datacat-0.5.dist-info/metadata.json
datacat-0.5.dist-info/top_level.txt
