Metadata-Version: 2.0
Name: datacat
Version: 0.5
Summary: Datacat client library
Home-page: http://srs.slac.stanford.edu
Author: Brian Van Klaveren
Author-email: bvan@slac.stanford.edu
License: SLAC BSD
Platform: UNKNOWN
Requires-Dist: requests
